{"nodes": [{"id": "quickstart_ws_init", "label": "ws init Command", "file_type": "document", "source_file": "apps/cli/docs/getting-started/quickstart.md", "source_location": null, "source_url": null, "captured_at": null, "author": null, "contributor": null}, {"id": "quickstart_ws_run", "label": "ws run Command", "file_type": "document", "source_file": "apps/cli/docs/getting-started/quickstart.md", "source_location": null, "source_url": null, "captured_at": null, "author": null, "contributor": null}, {"id": "quickstart_ws_dashboard", "label": "ws dashboard Command", "file_type": "document", "source_file": "apps/cli/docs/getting-started/quickstart.md", "source_location": null, "source_url": null, "captured_at": null, "author": null, "contributor": null}, {"id": "quickstart_ws_checkout", "label": "ws checkout Command", "file_type": "document", "source_file": "apps/cli/docs/getting-started/quickstart.md", "source_location": null, "source_url": null, "captured_at": null, "author": null, "contributor": null}, {"id": "quickstart_ws_destroy", "label": "ws destroy Command", "file_type": "document", "source_file": "apps/cli/docs/getting-started/quickstart.md", "source_location": null, "source_url": null, "captured_at": null, "author": null, "contributor": null}, {"id": "quickstart_workstream_yaml", "label": "workstream.yaml Config File", "file_type": "document", "source_file": "apps/cli/docs/getting-started/quickstart.md", "source_location": null, "source_url": null, "captured_at": null, "author": null, "contributor": null}], "edges": [{"source": "quickstart_ws_init", "target": "quickstart_workstream_yaml", "relation": "references", "confidence": "EXTRACTED", "confidence_score": 1.0, "source_file": "apps/cli/docs/getting-started/quickstart.md", "source_location": null, "weight": 1.0}, {"source": "quickstart_ws_run", "target": "concepts_git_worktree", "relation": "references", "confidence": "EXTRACTED", "confidence_score": 1.0, "source_file": "apps/cli/docs/getting-started/quickstart.md", "source_location": null, "weight": 1.0}, {"source": "quickstart_ws_run", "target": "concepts_branch_naming", "relation": "references", "confidence": "EXTRACTED", "confidence_score": 1.0, "source_file": "apps/cli/docs/getting-started/quickstart.md", "source_location": null, "weight": 1.0}, {"source": "quickstart_ws_dashboard", "target": "cli_docs_interactive_dashboard_feature", "relation": "references", "confidence": "INFERRED", "confidence_score": 0.85, "source_file": "apps/cli/docs/getting-started/quickstart.md", "source_location": null, "weight": 1.0}, {"source": "quickstart_workstream_yaml", "target": "config_agent_section", "relation": "references", "confidence": "INFERRED", "confidence_score": 0.9, "source_file": "apps/cli/docs/getting-started/quickstart.md", "source_location": null, "weight": 1.0}, {"source": "quickstart_workstream_yaml", "target": "config_workstreams_section", "relation": "references", "confidence": "INFERRED", "confidence_score": 0.9, "source_file": "apps/cli/docs/getting-started/quickstart.md", "source_location": null, "weight": 1.0}], "hyperedges": []}