{"nodes": [{"id": "uint", "label": "uint.ts", "file_type": "code", "source_file": "apps/desktop/src/vs/base/common/uint.ts", "source_location": "L1"}, {"id": "uint_touint8", "label": "toUint8()", "file_type": "code", "source_file": "apps/desktop/src/vs/base/common/uint.ts", "source_location": "L41"}, {"id": "uint_touint32", "label": "toUint32()", "file_type": "code", "source_file": "apps/desktop/src/vs/base/common/uint.ts", "source_location": "L51"}], "edges": [{"source": "uint", "target": "uint_touint8", "relation": "contains", "confidence": "EXTRACTED", "source_file": "apps/desktop/src/vs/base/common/uint.ts", "source_location": "L41", "weight": 1.0}, {"source": "uint", "target": "uint_touint32", "relation": "contains", "confidence": "EXTRACTED", "source_file": "apps/desktop/src/vs/base/common/uint.ts", "source_location": "L51", "weight": 1.0}]}