{"nodes": [{"id": "session_viewer", "label": "session-viewer.tsx", "file_type": "code", "source_file": "apps/cli/src/ui/session-viewer.tsx", "source_location": "L1"}, {"id": "session_viewer_spinner", "label": "Spinner()", "file_type": "code", "source_file": "apps/cli/src/ui/session-viewer.tsx", "source_location": "L62"}, {"id": "session_viewer_calcelapsed", "label": "calcElapsed()", "file_type": "code", "source_file": "apps/cli/src/ui/session-viewer.tsx", "source_location": "L78"}, {"id": "session_viewer_toolsummary", "label": "toolSummary()", "file_type": "code", "source_file": "apps/cli/src/ui/session-viewer.tsx", "source_location": "L104"}, {"id": "session_viewer_detectfiletype", "label": "detectFiletype()", "file_type": "code", "source_file": "apps/cli/src/ui/session-viewer.tsx", "source_location": "L150"}, {"id": "session_viewer_fmtduration", "label": "fmtDuration()", "file_type": "code", "source_file": "apps/cli/src/ui/session-viewer.tsx", "source_location": "L154"}, {"id": "session_viewer_fmtcost", "label": "fmtCost()", "file_type": "code", "source_file": "apps/cli/src/ui/session-viewer.tsx", "source_location": "L160"}, {"id": "session_viewer_stripansi", "label": "stripAnsi()", "file_type": "code", "source_file": "apps/cli/src/ui/session-viewer.tsx", "source_location": "L161"}, {"id": "session_viewer_inlinetool", "label": "InlineTool()", "file_type": "code", "source_file": "apps/cli/src/ui/session-viewer.tsx", "source_location": "L165"}, {"id": "session_viewer_check", "label": "check()", "file_type": "code", "source_file": "apps/cli/src/ui/session-viewer.tsx", "source_location": "L468"}, {"id": "session_viewer_refresh", "label": "refresh()", "file_type": "code", "source_file": "apps/cli/src/ui/session-viewer.tsx", "source_location": "L487"}, {"id": "session_viewer_go", "label": "go()", "file_type": "code", "source_file": "apps/cli/src/ui/session-viewer.tsx", "source_location": "L495"}], "edges": [{"source": "session_viewer", "target": "patch_terminal_dimensions_js", "relation": "imports_from", "confidence": "EXTRACTED", "source_file": "apps/cli/src/ui/session-viewer.tsx", "source_location": "L4", "weight": 1.0}, {"source": "session_viewer", "target": "react", "relation": "imports_from", "confidence": "EXTRACTED", "source_file": "apps/cli/src/ui/session-viewer.tsx", "source_location": "L6", "weight": 1.0}, {"source": "session_viewer", "target": "core", "relation": "imports_from", "confidence": "EXTRACTED", "source_file": "apps/cli/src/ui/session-viewer.tsx", "source_location": "L7", "weight": 1.0}, {"source": "session_viewer", "target": "react", "relation": "imports_from", "confidence": "EXTRACTED", "source_file": "apps/cli/src/ui/session-viewer.tsx", "source_location": "L13", "weight": 1.0}, {"source": "session_viewer", "target": "themes_js", "relation": "imports_from", "confidence": "EXTRACTED", "source_file": "apps/cli/src/ui/session-viewer.tsx", "source_location": "L19", "weight": 1.0}, {"source": "session_viewer", "target": "parsers_config_js", "relation": "imports_from", "confidence": "EXTRACTED", "source_file": "apps/cli/src/ui/session-viewer.tsx", "source_location": "L20", "weight": 1.0}, {"source": "session_viewer", "target": "diff", "relation": "imports_from", "confidence": "EXTRACTED", "source_file": "apps/cli/src/ui/session-viewer.tsx", "source_location": "L21", "weight": 1.0}, {"source": "session_viewer", "target": "path", "relation": "imports_from", "confidence": "EXTRACTED", "source_file": "apps/cli/src/ui/session-viewer.tsx", "source_location": "L22", "weight": 1.0}, {"source": "session_viewer", "target": "core", "relation": "imports_from", "confidence": "EXTRACTED", "source_file": "apps/cli/src/ui/session-viewer.tsx", "source_location": "L23", "weight": 1.0}, {"source": "session_viewer", "target": "core", "relation": "imports_from", "confidence": "EXTRACTED", "source_file": "apps/cli/src/ui/session-viewer.tsx", "source_location": "L24", "weight": 1.0}, {"source": "session_viewer", "target": "session_viewer_spinner", "relation": "contains", "confidence": "EXTRACTED", "source_file": "apps/cli/src/ui/session-viewer.tsx", "source_location": "L62", "weight": 1.0}, {"source": "session_viewer", "target": "session_viewer_calcelapsed", "relation": "contains", "confidence": "EXTRACTED", "source_file": "apps/cli/src/ui/session-viewer.tsx", "source_location": "L78", "weight": 1.0}, {"source": "session_viewer", "target": "session_viewer_toolsummary", "relation": "contains", "confidence": "EXTRACTED", "source_file": "apps/cli/src/ui/session-viewer.tsx", "source_location": "L104", "weight": 1.0}, {"source": "session_viewer", "target": "session_viewer_detectfiletype", "relation": "contains", "confidence": "EXTRACTED", "source_file": "apps/cli/src/ui/session-viewer.tsx", "source_location": "L150", "weight": 1.0}, {"source": "session_viewer", "target": "session_viewer_fmtduration", "relation": "contains", "confidence": "EXTRACTED", "source_file": "apps/cli/src/ui/session-viewer.tsx", "source_location": "L154", "weight": 1.0}, {"source": "session_viewer", "target": "session_viewer_fmtcost", "relation": "contains", "confidence": "EXTRACTED", "source_file": "apps/cli/src/ui/session-viewer.tsx", "source_location": "L160", "weight": 1.0}, {"source": "session_viewer", "target": "session_viewer_stripansi", "relation": "contains", "confidence": "EXTRACTED", "source_file": "apps/cli/src/ui/session-viewer.tsx", "source_location": "L161", "weight": 1.0}, {"source": "session_viewer", "target": "session_viewer_inlinetool", "relation": "contains", "confidence": "EXTRACTED", "source_file": "apps/cli/src/ui/session-viewer.tsx", "source_location": "L165", "weight": 1.0}, {"source": "session_viewer", "target": "session_viewer_check", "relation": "contains", "confidence": "EXTRACTED", "source_file": "apps/cli/src/ui/session-viewer.tsx", "source_location": "L468", "weight": 1.0}, {"source": "session_viewer", "target": "session_viewer_refresh", "relation": "contains", "confidence": "EXTRACTED", "source_file": "apps/cli/src/ui/session-viewer.tsx", "source_location": "L487", "weight": 1.0}, {"source": "session_viewer", "target": "session_viewer_go", "relation": "contains", "confidence": "EXTRACTED", "source_file": "apps/cli/src/ui/session-viewer.tsx", "source_location": "L495", "weight": 1.0}, {"source": "session_viewer", "target": "session_viewer_refresh", "relation": "contains", "confidence": "EXTRACTED", "source_file": "apps/cli/src/ui/session-viewer.tsx", "source_location": "L601", "weight": 1.0}, {"source": "session_viewer", "target": "session_viewer_go", "relation": "contains", "confidence": "EXTRACTED", "source_file": "apps/cli/src/ui/session-viewer.tsx", "source_location": "L605", "weight": 1.0}]}