{"nodes": [{"id": "exthost_common_services", "label": "extHost.common.services.ts", "file_type": "code", "source_file": "apps/desktop/src/vs/workbench/api/common/extHost.common.services.ts", "source_location": "L1"}], "edges": [{"source": "exthost_common_services", "target": "extensions_js", "relation": "imports_from", "confidence": "EXTRACTED", "source_file": "apps/desktop/src/vs/workbench/api/common/extHost.common.services.ts", "source_location": "L6", "weight": 1.0}, {"source": "exthost_common_services", "target": "exthostoutput_js", "relation": "imports_from", "confidence": "EXTRACTED", "source_file": "apps/desktop/src/vs/workbench/api/common/extHost.common.services.ts", "source_location": "L7", "weight": 1.0}, {"source": "exthost_common_services", "target": "exthostworkspace_js", "relation": "imports_from", "confidence": "EXTRACTED", "source_file": "apps/desktop/src/vs/workbench/api/common/extHost.common.services.ts", "source_location": "L8", "weight": 1.0}, {"source": "exthost_common_services", "target": "exthostdecorations_js", "relation": "imports_from", "confidence": "EXTRACTED", "source_file": "apps/desktop/src/vs/workbench/api/common/extHost.common.services.ts", "source_location": "L9", "weight": 1.0}, {"source": "exthost_common_services", "target": "exthostconfiguration_js", "relation": "imports_from", "confidence": "EXTRACTED", "source_file": "apps/desktop/src/vs/workbench/api/common/extHost.common.services.ts", "source_location": "L10", "weight": 1.0}, {"source": "exthost_common_services", "target": "exthostcommands_js", "relation": "imports_from", "confidence": "EXTRACTED", "source_file": "apps/desktop/src/vs/workbench/api/common/extHost.common.services.ts", "source_location": "L11", "weight": 1.0}, {"source": "exthost_common_services", "target": "exthostdocumentsandeditors_js", "relation": "imports_from", "confidence": "EXTRACTED", "source_file": "apps/desktop/src/vs/workbench/api/common/extHost.common.services.ts", "source_location": "L12", "weight": 1.0}, {"source": "exthost_common_services", "target": "exthostterminalservice_js", "relation": "imports_from", "confidence": "EXTRACTED", "source_file": "apps/desktop/src/vs/workbench/api/common/extHost.common.services.ts", "source_location": "L13", "weight": 1.0}, {"source": "exthost_common_services", "target": "exthosttask_js", "relation": "imports_from", "confidence": "EXTRACTED", "source_file": "apps/desktop/src/vs/workbench/api/common/extHost.common.services.ts", "source_location": "L14", "weight": 1.0}, {"source": "exthost_common_services", "target": "exthostdebugservice_js", "relation": "imports_from", "confidence": "EXTRACTED", "source_file": "apps/desktop/src/vs/workbench/api/common/extHost.common.services.ts", "source_location": "L15", "weight": 1.0}, {"source": "exthost_common_services", "target": "exthostsearch_js", "relation": "imports_from", "confidence": "EXTRACTED", "source_file": "apps/desktop/src/vs/workbench/api/common/extHost.common.services.ts", "source_location": "L16", "weight": 1.0}, {"source": "exthost_common_services", "target": "exthoststorage_js", "relation": "imports_from", "confidence": "EXTRACTED", "source_file": "apps/desktop/src/vs/workbench/api/common/extHost.common.services.ts", "source_location": "L17", "weight": 1.0}, {"source": "exthost_common_services", "target": "exthosttunnelservice_js", "relation": "imports_from", "confidence": "EXTRACTED", "source_file": "apps/desktop/src/vs/workbench/api/common/extHost.common.services.ts", "source_location": "L18", "weight": 1.0}, {"source": "exthost_common_services", "target": "exthostapideprecationservice_js", "relation": "imports_from", "confidence": "EXTRACTED", "source_file": "apps/desktop/src/vs/workbench/api/common/extHost.common.services.ts", "source_location": "L19", "weight": 1.0}, {"source": "exthost_common_services", "target": "exthostwindow_js", "relation": "imports_from", "confidence": "EXTRACTED", "source_file": "apps/desktop/src/vs/workbench/api/common/extHost.common.services.ts", "source_location": "L20", "weight": 1.0}, {"source": "exthost_common_services", "target": "exthostpower_js", "relation": "imports_from", "confidence": "EXTRACTED", "source_file": "apps/desktop/src/vs/workbench/api/common/extHost.common.services.ts", "source_location": "L21", "weight": 1.0}, {"source": "exthost_common_services", "target": "exthostfilesystemconsumer_js", "relation": "imports_from", "confidence": "EXTRACTED", "source_file": "apps/desktop/src/vs/workbench/api/common/extHost.common.services.ts", "source_location": "L22", "weight": 1.0}, {"source": "exthost_common_services", "target": "exthostfilesysteminfo_js", "relation": "imports_from", "confidence": "EXTRACTED", "source_file": "apps/desktop/src/vs/workbench/api/common/extHost.common.services.ts", "source_location": "L23", "weight": 1.0}, {"source": "exthost_common_services", "target": "exthostsecretstate_js", "relation": "imports_from", "confidence": "EXTRACTED", "source_file": "apps/desktop/src/vs/workbench/api/common/extHost.common.services.ts", "source_location": "L24", "weight": 1.0}, {"source": "exthost_common_services", "target": "exthosteditortabs_js", "relation": "imports_from", "confidence": "EXTRACTED", "source_file": "apps/desktop/src/vs/workbench/api/common/extHost.common.services.ts", "source_location": "L25", "weight": 1.0}, {"source": "exthost_common_services", "target": "exthostloggerservice_js", "relation": "imports_from", "confidence": "EXTRACTED", "source_file": "apps/desktop/src/vs/workbench/api/common/extHost.common.services.ts", "source_location": "L26", "weight": 1.0}, {"source": "exthost_common_services", "target": "log_js", "relation": "imports_from", "confidence": "EXTRACTED", "source_file": "apps/desktop/src/vs/workbench/api/common/extHost.common.services.ts", "source_location": "L27", "weight": 1.0}, {"source": "exthost_common_services", "target": "exthostvariableresolverservice_js", "relation": "imports_from", "confidence": "EXTRACTED", "source_file": "apps/desktop/src/vs/workbench/api/common/extHost.common.services.ts", "source_location": "L28", "weight": 1.0}, {"source": "exthost_common_services", "target": "exthostlocalizationservice_js", "relation": "imports_from", "confidence": "EXTRACTED", "source_file": "apps/desktop/src/vs/workbench/api/common/extHost.common.services.ts", "source_location": "L29", "weight": 1.0}, {"source": "exthost_common_services", "target": "exthostmanagedsockets_js", "relation": "imports_from", "confidence": "EXTRACTED", "source_file": "apps/desktop/src/vs/workbench/api/common/extHost.common.services.ts", "source_location": "L30", "weight": 1.0}, {"source": "exthost_common_services", "target": "exthostlanguagemodels_js", "relation": "imports_from", "confidence": "EXTRACTED", "source_file": "apps/desktop/src/vs/workbench/api/common/extHost.common.services.ts", "source_location": "L31", "weight": 1.0}, {"source": "exthost_common_services", "target": "exthostterminalshellintegration_js", "relation": "imports_from", "confidence": "EXTRACTED", "source_file": "apps/desktop/src/vs/workbench/api/common/extHost.common.services.ts", "source_location": "L32", "weight": 1.0}, {"source": "exthost_common_services", "target": "exthosttesting_js", "relation": "imports_from", "confidence": "EXTRACTED", "source_file": "apps/desktop/src/vs/workbench/api/common/extHost.common.services.ts", "source_location": "L33", "weight": 1.0}, {"source": "exthost_common_services", "target": "exthostmcp_js", "relation": "imports_from", "confidence": "EXTRACTED", "source_file": "apps/desktop/src/vs/workbench/api/common/extHost.common.services.ts", "source_location": "L34", "weight": 1.0}, {"source": "exthost_common_services", "target": "exthosturls_js", "relation": "imports_from", "confidence": "EXTRACTED", "source_file": "apps/desktop/src/vs/workbench/api/common/extHost.common.services.ts", "source_location": "L35", "weight": 1.0}, {"source": "exthost_common_services", "target": "exthostprogress_js", "relation": "imports_from", "confidence": "EXTRACTED", "source_file": "apps/desktop/src/vs/workbench/api/common/extHost.common.services.ts", "source_location": "L36", "weight": 1.0}, {"source": "exthost_common_services", "target": "exthostdatachannels_js", "relation": "imports_from", "confidence": "EXTRACTED", "source_file": "apps/desktop/src/vs/workbench/api/common/extHost.common.services.ts", "source_location": "L37", "weight": 1.0}, {"source": "exthost_common_services", "target": "exthostmeteredconnection_js", "relation": "imports_from", "confidence": "EXTRACTED", "source_file": "apps/desktop/src/vs/workbench/api/common/extHost.common.services.ts", "source_location": "L38", "weight": 1.0}, {"source": "exthost_common_services", "target": "exthostgitextensionservice_js", "relation": "imports_from", "confidence": "EXTRACTED", "source_file": "apps/desktop/src/vs/workbench/api/common/extHost.common.services.ts", "source_location": "L39", "weight": 1.0}]}