{"nodes": [{"id": "ansi", "label": "ansi.ts", "file_type": "code", "source_file": "apps/cli/src/ui/ansi.ts", "source_location": "L1"}, {"id": "ansi_bg256", "label": "bg256()", "file_type": "code", "source_file": "apps/cli/src/ui/ansi.ts", "source_location": "L27"}, {"id": "ansi_fg256", "label": "fg256()", "file_type": "code", "source_file": "apps/cli/src/ui/ansi.ts", "source_location": "L28"}, {"id": "ansi_moveto", "label": "moveTo()", "file_type": "code", "source_file": "apps/cli/src/ui/ansi.ts", "source_location": "L35"}, {"id": "ansi_clearscreen", "label": "clearScreen()", "file_type": "code", "source_file": "apps/cli/src/ui/ansi.ts", "source_location": "L38"}, {"id": "ansi_hidecursor", "label": "hideCursor()", "file_type": "code", "source_file": "apps/cli/src/ui/ansi.ts", "source_location": "L41"}, {"id": "ansi_showcursor", "label": "showCursor()", "file_type": "code", "source_file": "apps/cli/src/ui/ansi.ts", "source_location": "L44"}, {"id": "ansi_enteraltscreen", "label": "enterAltScreen()", "file_type": "code", "source_file": "apps/cli/src/ui/ansi.ts", "source_location": "L47"}, {"id": "ansi_exitaltscreen", "label": "exitAltScreen()", "file_type": "code", "source_file": "apps/cli/src/ui/ansi.ts", "source_location": "L50"}, {"id": "ansi_stripansi", "label": "stripAnsi()", "file_type": "code", "source_file": "apps/cli/src/ui/ansi.ts", "source_location": "L54"}, {"id": "ansi_truncate", "label": "truncate()", "file_type": "code", "source_file": "apps/cli/src/ui/ansi.ts", "source_location": "L58"}, {"id": "ansi_pad", "label": "pad()", "file_type": "code", "source_file": "apps/cli/src/ui/ansi.ts", "source_location": "L63"}], "edges": [{"source": "ansi", "target": "ansi_bg256", "relation": "contains", "confidence": "EXTRACTED", "source_file": "apps/cli/src/ui/ansi.ts", "source_location": "L27", "weight": 1.0}, {"source": "ansi", "target": "ansi_fg256", "relation": "contains", "confidence": "EXTRACTED", "source_file": "apps/cli/src/ui/ansi.ts", "source_location": "L28", "weight": 1.0}, {"source": "ansi", "target": "ansi_moveto", "relation": "contains", "confidence": "EXTRACTED", "source_file": "apps/cli/src/ui/ansi.ts", "source_location": "L35", "weight": 1.0}, {"source": "ansi", "target": "ansi_clearscreen", "relation": "contains", "confidence": "EXTRACTED", "source_file": "apps/cli/src/ui/ansi.ts", "source_location": "L38", "weight": 1.0}, {"source": "ansi", "target": "ansi_hidecursor", "relation": "contains", "confidence": "EXTRACTED", "source_file": "apps/cli/src/ui/ansi.ts", "source_location": "L41", "weight": 1.0}, {"source": "ansi", "target": "ansi_showcursor", "relation": "contains", "confidence": "EXTRACTED", "source_file": "apps/cli/src/ui/ansi.ts", "source_location": "L44", "weight": 1.0}, {"source": "ansi", "target": "ansi_enteraltscreen", "relation": "contains", "confidence": "EXTRACTED", "source_file": "apps/cli/src/ui/ansi.ts", "source_location": "L47", "weight": 1.0}, {"source": "ansi", "target": "ansi_exitaltscreen", "relation": "contains", "confidence": "EXTRACTED", "source_file": "apps/cli/src/ui/ansi.ts", "source_location": "L50", "weight": 1.0}, {"source": "ansi", "target": "ansi_stripansi", "relation": "contains", "confidence": "EXTRACTED", "source_file": "apps/cli/src/ui/ansi.ts", "source_location": "L54", "weight": 1.0}, {"source": "ansi", "target": "ansi_truncate", "relation": "contains", "confidence": "EXTRACTED", "source_file": "apps/cli/src/ui/ansi.ts", "source_location": "L58", "weight": 1.0}, {"source": "ansi", "target": "ansi_pad", "relation": "contains", "confidence": "EXTRACTED", "source_file": "apps/cli/src/ui/ansi.ts", "source_location": "L63", "weight": 1.0}, {"source": "ansi_clearscreen", "target": "ansi_moveto", "relation": "calls", "confidence": "EXTRACTED", "source_file": "apps/cli/src/ui/ansi.ts", "source_location": "L39", "weight": 1.0}, {"source": "ansi_pad", "target": "ansi_stripansi", "relation": "calls", "confidence": "EXTRACTED", "source_file": "apps/cli/src/ui/ansi.ts", "source_location": "L64", "weight": 1.0}]}