{"nodes": [{"id": "update_service", "label": "update_service.rs", "file_type": "code", "source_file": "apps/desktop/cli/src/update_service.rs", "source_location": "L1"}, {"id": "update_service_updateservice", "label": "UpdateService", "file_type": "code", "source_file": "apps/desktop/cli/src/update_service.rs", "source_location": "L24"}, {"id": "update_service_release", "label": "Release", "file_type": "code", "source_file": "apps/desktop/cli/src/update_service.rs", "source_location": "L31"}, {"id": "update_service_release_fmt", "label": ".fmt()", "file_type": "code", "source_file": "apps/desktop/cli/src/update_service.rs", "source_location": "L40"}, {"id": "update_service_updateserverversion", "label": "UpdateServerVersion", "file_type": "code", "source_file": "apps/desktop/cli/src/update_service.rs", "source_location": "L46"}, {"id": "update_service_quality_download_segment", "label": "quality_download_segment()", "file_type": "code", "source_file": "apps/desktop/cli/src/update_service.rs", "source_location": "L51"}, {"id": "update_service_get_update_endpoint", "label": "get_update_endpoint()", "file_type": "code", "source_file": "apps/desktop/cli/src/update_service.rs", "source_location": "L59"}, {"id": "update_service_updateservice_new", "label": ".new()", "file_type": "code", "source_file": "apps/desktop/cli/src/update_service.rs", "source_location": "L71"}, {"id": "update_service_updateservice_get_release_by_semver_version", "label": ".get_release_by_semver_version()", "file_type": "code", "source_file": "apps/desktop/cli/src/update_service.rs", "source_location": "L75"}, {"id": "update_service_updateservice_get_latest_commit", "label": ".get_latest_commit()", "file_type": "code", "source_file": "apps/desktop/cli/src/update_service.rs", "source_location": "L117"}, {"id": "update_service_updateservice_get_download_stream", "label": ".get_download_stream()", "file_type": "code", "source_file": "apps/desktop/cli/src/update_service.rs", "source_location": "L157"}, {"id": "update_service_unzip_downloaded_release", "label": "unzip_downloaded_release()", "file_type": "code", "source_file": "apps/desktop/cli/src/update_service.rs", "source_location": "L181"}, {"id": "update_service_targetkind", "label": "TargetKind", "file_type": "code", "source_file": "apps/desktop/cli/src/update_service.rs", "source_location": "L197"}, {"id": "update_service_targetkind_download_segment", "label": ".download_segment()", "file_type": "code", "source_file": "apps/desktop/cli/src/update_service.rs", "source_location": "L205"}, {"id": "update_service_platform", "label": "Platform", "file_type": "code", "source_file": "apps/desktop/cli/src/update_service.rs", "source_location": "L216"}, {"id": "update_service_platform_archive", "label": ".archive()", "file_type": "code", "source_file": "apps/desktop/cli/src/update_service.rs", "source_location": "L233"}, {"id": "update_service_platform_headless", "label": ".headless()", "file_type": "code", "source_file": "apps/desktop/cli/src/update_service.rs", "source_location": "L246"}, {"id": "update_service_platform_cli", "label": ".cli()", "file_type": "code", "source_file": "apps/desktop/cli/src/update_service.rs", "source_location": "L265"}, {"id": "update_service_platform_web", "label": ".web()", "file_type": "code", "source_file": "apps/desktop/cli/src/update_service.rs", "source_location": "L284"}, {"id": "update_service_platform_env_default", "label": ".env_default()", "file_type": "code", "source_file": "apps/desktop/cli/src/update_service.rs", "source_location": "L288"}, {"id": "update_service_platform_fmt", "label": ".fmt()", "file_type": "code", "source_file": "apps/desktop/cli/src/update_service.rs", "source_location": "L324"}], "edges": [{"source": "update_service", "target": "std", "relation": "imports_from", "confidence": "EXTRACTED", "source_file": "apps/desktop/cli/src/update_service.rs", "source_location": "L6", "weight": 1.0}, {"source": "update_service", "target": "serde", "relation": "imports_from", "confidence": "EXTRACTED", "source_file": "apps/desktop/cli/src/update_service.rs", "source_location": "L8", "weight": 1.0}, {"source": "update_service", "target": "crate", "relation": "imports_from", "confidence": "EXTRACTED", "source_file": "apps/desktop/cli/src/update_service.rs", "source_location": "L10", "weight": 1.0}, {"source": "update_service", "target": "update_service_updateservice", "relation": "contains", "confidence": "EXTRACTED", "source_file": "apps/desktop/cli/src/update_service.rs", "source_location": "L24", "weight": 1.0}, {"source": "update_service", "target": "update_service_release", "relation": "contains", "confidence": "EXTRACTED", "source_file": "apps/desktop/cli/src/update_service.rs", "source_location": "L31", "weight": 1.0}, {"source": "update_service_release", "target": "update_service_release_fmt", "relation": "method", "confidence": "EXTRACTED", "source_file": "apps/desktop/cli/src/update_service.rs", "source_location": "L40", "weight": 1.0}, {"source": "update_service", "target": "update_service_updateserverversion", "relation": "contains", "confidence": "EXTRACTED", "source_file": "apps/desktop/cli/src/update_service.rs", "source_location": "L46", "weight": 1.0}, {"source": "update_service", "target": "update_service_quality_download_segment", "relation": "contains", "confidence": "EXTRACTED", "source_file": "apps/desktop/cli/src/update_service.rs", "source_location": "L51", "weight": 1.0}, {"source": "update_service", "target": "update_service_get_update_endpoint", "relation": "contains", "confidence": "EXTRACTED", "source_file": "apps/desktop/cli/src/update_service.rs", "source_location": "L59", "weight": 1.0}, {"source": "update_service_updateservice", "target": "update_service_updateservice_new", "relation": "method", "confidence": "EXTRACTED", "source_file": "apps/desktop/cli/src/update_service.rs", "source_location": "L71", "weight": 1.0}, {"source": "update_service_updateservice", "target": "update_service_updateservice_get_release_by_semver_version", "relation": "method", "confidence": "EXTRACTED", "source_file": "apps/desktop/cli/src/update_service.rs", "source_location": "L75", "weight": 1.0}, {"source": "update_service_updateservice", "target": "update_service_updateservice_get_latest_commit", "relation": "method", "confidence": "EXTRACTED", "source_file": "apps/desktop/cli/src/update_service.rs", "source_location": "L117", "weight": 1.0}, {"source": "update_service_updateservice", "target": "update_service_updateservice_get_download_stream", "relation": "method", "confidence": "EXTRACTED", "source_file": "apps/desktop/cli/src/update_service.rs", "source_location": "L157", "weight": 1.0}, {"source": "update_service", "target": "update_service_unzip_downloaded_release", "relation": "contains", "confidence": "EXTRACTED", "source_file": "apps/desktop/cli/src/update_service.rs", "source_location": "L181", "weight": 1.0}, {"source": "update_service", "target": "update_service_targetkind", "relation": "contains", "confidence": "EXTRACTED", "source_file": "apps/desktop/cli/src/update_service.rs", "source_location": "L197", "weight": 1.0}, {"source": "update_service_targetkind", "target": "update_service_targetkind_download_segment", "relation": "method", "confidence": "EXTRACTED", "source_file": "apps/desktop/cli/src/update_service.rs", "source_location": "L205", "weight": 1.0}, {"source": "update_service", "target": "update_service_platform", "relation": "contains", "confidence": "EXTRACTED", "source_file": "apps/desktop/cli/src/update_service.rs", "source_location": "L216", "weight": 1.0}, {"source": "update_service_platform", "target": "update_service_platform_archive", "relation": "method", "confidence": "EXTRACTED", "source_file": "apps/desktop/cli/src/update_service.rs", "source_location": "L233", "weight": 1.0}, {"source": "update_service_platform", "target": "update_service_platform_headless", "relation": "method", "confidence": "EXTRACTED", "source_file": "apps/desktop/cli/src/update_service.rs", "source_location": "L246", "weight": 1.0}, {"source": "update_service_platform", "target": "update_service_platform_cli", "relation": "method", "confidence": "EXTRACTED", "source_file": "apps/desktop/cli/src/update_service.rs", "source_location": "L265", "weight": 1.0}, {"source": "update_service_platform", "target": "update_service_platform_web", "relation": "method", "confidence": "EXTRACTED", "source_file": "apps/desktop/cli/src/update_service.rs", "source_location": "L284", "weight": 1.0}, {"source": "update_service_platform", "target": "update_service_platform_env_default", "relation": "method", "confidence": "EXTRACTED", "source_file": "apps/desktop/cli/src/update_service.rs", "source_location": "L288", "weight": 1.0}, {"source": "update_service_platform", "target": "update_service_platform_fmt", "relation": "method", "confidence": "EXTRACTED", "source_file": "apps/desktop/cli/src/update_service.rs", "source_location": "L324", "weight": 1.0}, {"source": "update_service_updateservice_get_release_by_semver_version", "target": "update_service_get_update_endpoint", "relation": "calls", "confidence": "EXTRACTED", "source_file": "apps/desktop/cli/src/update_service.rs", "source_location": "L82", "weight": 1.0}, {"source": "update_service_updateservice_get_release_by_semver_version", "target": "update_service_targetkind_download_segment", "relation": "calls", "confidence": "EXTRACTED", "source_file": "apps/desktop/cli/src/update_service.rs", "source_location": "L83", "weight": 1.0}, {"source": "update_service_updateservice_get_latest_commit", "target": "update_service_get_update_endpoint", "relation": "calls", "confidence": "EXTRACTED", "source_file": "apps/desktop/cli/src/update_service.rs", "source_location": "L123", "weight": 1.0}, {"source": "update_service_updateservice_get_latest_commit", "target": "update_service_targetkind_download_segment", "relation": "calls", "confidence": "EXTRACTED", "source_file": "apps/desktop/cli/src/update_service.rs", "source_location": "L124", "weight": 1.0}, {"source": "update_service_updateservice_get_download_stream", "target": "update_service_get_update_endpoint", "relation": "calls", "confidence": "EXTRACTED", "source_file": "apps/desktop/cli/src/update_service.rs", "source_location": "L158", "weight": 1.0}, {"source": "update_service_updateservice_get_download_stream", "target": "update_service_targetkind_download_segment", "relation": "calls", "confidence": "EXTRACTED", "source_file": "apps/desktop/cli/src/update_service.rs", "source_location": "L159", "weight": 1.0}, {"source": "update_service_targetkind_download_segment", "target": "update_service_platform_headless", "relation": "calls", "confidence": "EXTRACTED", "source_file": "apps/desktop/cli/src/update_service.rs", "source_location": "L207", "weight": 1.0}, {"source": "update_service_targetkind_download_segment", "target": "update_service_platform_archive", "relation": "calls", "confidence": "EXTRACTED", "source_file": "apps/desktop/cli/src/update_service.rs", "source_location": "L208", "weight": 1.0}, {"source": "update_service_targetkind_download_segment", "target": "update_service_platform_web", "relation": "calls", "confidence": "EXTRACTED", "source_file": "apps/desktop/cli/src/update_service.rs", "source_location": "L209", "weight": 1.0}, {"source": "update_service_targetkind_download_segment", "target": "update_service_platform_cli", "relation": "calls", "confidence": "EXTRACTED", "source_file": "apps/desktop/cli/src/update_service.rs", "source_location": "L210", "weight": 1.0}]}