{"nodes": [{"id": "updatetag", "label": "updateTag.ts", "file_type": "code", "source_file": "apps/desktop/extensions/emmet/src/updateTag.ts", "source_location": "L1"}, {"id": "updatetag_updatetag", "label": "updateTag()", "file_type": "code", "source_file": "apps/desktop/extensions/emmet/src/updateTag.ts", "source_location": "L16"}, {"id": "updatetag_getrangesfromnode", "label": "getRangesFromNode()", "file_type": "code", "source_file": "apps/desktop/extensions/emmet/src/updateTag.ts", "source_location": "L56"}, {"id": "updatetag_getrangestoupdate", "label": "getRangesToUpdate()", "file_type": "code", "source_file": "apps/desktop/extensions/emmet/src/updateTag.ts", "source_location": "L76"}], "edges": [{"source": "updatetag", "target": "vscode", "relation": "imports_from", "confidence": "EXTRACTED", "source_file": "apps/desktop/extensions/emmet/src/updateTag.ts", "source_location": "L6", "weight": 1.0}, {"source": "updatetag", "target": "util", "relation": "imports_from", "confidence": "EXTRACTED", "source_file": "apps/desktop/extensions/emmet/src/updateTag.ts", "source_location": "L7", "weight": 1.0}, {"source": "updatetag", "target": "emmetflatnode", "relation": "imports_from", "confidence": "EXTRACTED", "source_file": "apps/desktop/extensions/emmet/src/updateTag.ts", "source_location": "L8", "weight": 1.0}, {"source": "updatetag", "target": "parsedocument", "relation": "imports_from", "confidence": "EXTRACTED", "source_file": "apps/desktop/extensions/emmet/src/updateTag.ts", "source_location": "L9", "weight": 1.0}, {"source": "updatetag", "target": "updatetag_updatetag", "relation": "contains", "confidence": "EXTRACTED", "source_file": "apps/desktop/extensions/emmet/src/updateTag.ts", "source_location": "L16", "weight": 1.0}, {"source": "updatetag", "target": "updatetag_getrangesfromnode", "relation": "contains", "confidence": "EXTRACTED", "source_file": "apps/desktop/extensions/emmet/src/updateTag.ts", "source_location": "L56", "weight": 1.0}, {"source": "updatetag", "target": "updatetag_getrangestoupdate", "relation": "contains", "confidence": "EXTRACTED", "source_file": "apps/desktop/extensions/emmet/src/updateTag.ts", "source_location": "L76", "weight": 1.0}, {"source": "updatetag_getrangestoupdate", "target": "updatetag_getrangesfromnode", "relation": "calls", "confidence": "EXTRACTED", "source_file": "apps/desktop/extensions/emmet/src/updateTag.ts", "source_location": "L83", "weight": 1.0}]}